esteria_api_client-0.0.11.dist-info/METADATA
esteria_api_client-0.0.11.dist-info/WHEEL
esteria_api_client-0.0.11.dist-info/licenses/LICENSE
esteria_api_client/__init__.py
esteria_api_client/esteria_api_client.cpython-314-darwin.so
esteria_api_client-0.0.11.dist-info/RECORD
