Metadata-Version: 2.4
Name: esteria-api-client
Version: 0.0.11
Classifier: Programming Language :: Rust
Classifier: Programming Language :: Python :: Implementation :: CPython
Classifier: Programming Language :: Python :: 3
Classifier: Programming Language :: Python :: 3.13
Classifier: Programming Language :: Python :: 3.14
License-File: LICENSE
Summary: A Rust client library for Esteria API with Python bindings
Keywords: sms,esteria,api
Author-email: Olegs Korsaks <bixority@gmail.com>
Requires-Python: >=3.13.9, <3.15.0
Project-URL: Homepage, https://github.com/bixority/esteria-api-client
Project-URL: Repository, https://github.com/bixority/esteria-api-client
Project-URL: Documentation, https://github.com/bixority/esteria-api-client/blob/main/README.md
